MANIFEST.in
requirements.txt
setup.py
email_templates.egg-info/PKG-INFO
email_templates.egg-info/SOURCES.txt
email_templates.egg-info/dependency_links.txt
email_templates.egg-info/not-zip-safe
email_templates.egg-info/top_level.txt
emailtemplates/__init__.py
emailtemplates/static/email-templates/bg-error.png
emailtemplates/static/email-templates/bg-info.png
emailtemplates/static/email-templates/bg-warning.png
emailtemplates/templates/.DS_Store
emailtemplates/templates/email/base.html
emailtemplates/templates/email/error.html
emailtemplates/templates/email/info.html
emailtemplates/templates/email/warning.html