Metadata-Version: 1.0
Name: email_templates
Version: 0.2.2
Summary: Django email templates
Home-page: UNKNOWN
Author: UNKNOWN
Author-email: UNKNOWN
License: UNKNOWN
Platform: any
